{
  "parent": "minecraft:item/generated",
  "textures": {
    "layer0": "yuushya:item/ft_zp"
  },
      "overrides": [
        { "predicate": { "direction": 0 }, "model": "yuushya:item/ft_zp" },
        { "predicate": { "direction": 0.1 }, "model": "yuushya:item/ft_xm" },
        { "predicate": { "direction": 0.2 }, "model": "yuushya:item/ft_yp" },
        { "predicate": { "direction": 0.3 }, "model": "yuushya:item/ft_ym" },
        { "predicate": { "direction": 0.4 }, "model": "yuushya:item/ft_zp" },
        { "predicate": { "direction": 0.5 }, "model": "yuushya:item/ft_zm" },
        { "predicate": { "direction": 0.6 }, "model": "yuushya:item/ft_rotatez" },
        { "predicate": { "direction": 0.7 }, "model": "yuushya:item/ft_rotatey" },
        { "predicate": { "direction": 0.8 }, "model": "yuushya:item/ft_rotatex" }
	]
}